metrics/__init__.py
metrics/bem.py
metrics/cfm.py
metrics/em.py
metrics/f1.py
metrics/utils/__init__.py
metrics/utils/tools.py
qa_evaluators-0.1.7.dist-info/LICENSE
qa_evaluators-0.1.7.dist-info/METADATA
qa_evaluators-0.1.7.dist-info/WHEEL
qa_evaluators-0.1.7.dist-info/top_level.txt
qa_evaluators-0.1.7.dist-info/RECORD
